.VERSION
AUTHORS.rst
CONTRIBUTING.rst
HISTORY.rst
LICENSE
MANIFEST.in
Pipfile
Pipfile.lock
README.rst
USAGE.rst
dev-requirements.txt
requirements.txt
setup.cfg
setup.py
docs/Makefile
docs/authors.rst
docs/conf.py
docs/contributing.rst
docs/history.rst
docs/index.rst
docs/installation.rst
docs/readme.rst
docs/usage.rst
tests/test_wikiseriesbrentlib.py
wikiseriesbrentlib/.VERSION
wikiseriesbrentlib/AUTHORS.rst
wikiseriesbrentlib/CONTRIBUTING.rst
wikiseriesbrentlib/HISTORY.rst
wikiseriesbrentlib/LICENSE
wikiseriesbrentlib/Pipfile
wikiseriesbrentlib/Pipfile.lock
wikiseriesbrentlib/README.rst
wikiseriesbrentlib/USAGE.rst
wikiseriesbrentlib/__init__.py
wikiseriesbrentlib/_version.py
wikiseriesbrentlib/dev-requirements.txt
wikiseriesbrentlib/requirements.txt
wikiseriesbrentlib/wikiseriesbrentlib.py
wikiseriesbrentlib/wikiseriesbrentlibexceptions.py
wikiseriesbrentlib.egg-info/PKG-INFO
wikiseriesbrentlib.egg-info/SOURCES.txt
wikiseriesbrentlib.egg-info/dependency_links.txt
wikiseriesbrentlib.egg-info/not-zip-safe
wikiseriesbrentlib.egg-info/requires.txt
wikiseriesbrentlib.egg-info/top_level.txt