Metadata-Version: 2.1
Name: wikiseriesbrentlib
Version: 0.1.0
Summary: A library interfacing with wikipedia to retrieve tv series information
Home-page: https://github.com/narvyk/wikiseriesbrentlib
Author: Brent De Cubber
Author-email: noneofyabusiness@gmail.com
License: MIT
Keywords: wikiseriesbrentlib
Classifier: Development Status :: 3 - Alpha
Classifier: Intended Audience :: Developers
Classifier: License :: OSI Approved :: MIT License
Classifier: Natural Language :: English
Classifier: Programming Language :: Python :: 3.9
License-File: LICENSE
License-File: AUTHORS.rst
